chunkipy/__init__.py
chunkipy/size_estimators/__init__.py
chunkipy/size_estimators/base_size_estimator.py
chunkipy/size_estimators/char_size_estimator.py
chunkipy/size_estimators/openai_size_estimator.py
chunkipy/size_estimators/word_size_estimator.py
chunkipy/text_chunker/__init__.py
chunkipy/text_chunker/data_models.py
chunkipy/text_chunker/text_chunker.py
chunkipy/text_splitters/__init__.py
chunkipy/text_splitters/base_text_splitter.py
chunkipy/text_splitters/basic_text_splitters.py
chunkipy/text_splitters/semantic/__init__.py
chunkipy/text_splitters/semantic/base_semantic_text_splitter.py
chunkipy/text_splitters/semantic/sentences/__init__.py
chunkipy/text_splitters/semantic/sentences/spacy_sentences_text_splitter.py
chunkipy/text_splitters/semantic/sentences/stanza_sentences_text_splitter.py
chunkipy/utils.py
chunkipy-1.1.0.dist-info/LICENSE
chunkipy-1.1.0.dist-info/METADATA
chunkipy-1.1.0.dist-info/WHEEL
chunkipy-1.1.0.dist-info/RECORD
