Metadata-Version: 2.3
Name: chunkipy
Version: 1.1.0
Summary: Chunkipy is an easy-to-use library for chunking text based on the size estimator function you provide.
License: MIT
Keywords: text,chunking,NLP,tokenization
Author: Gioele Crispo
Author-email: crispogioele@gmail.com
Requires-Python: >=3.10,<3.13
Classifier: Development Status :: 5 - Production/Stable
Classifier: Intended Audience :: Developers
Classifier: License :: OSI Approved :: MIT License
Classifier: Programming Language :: Python
Classifier: Programming Language :: Python :: 3
Classifier: Programming Language :: Python :: 3.10
Classifier: Programming Language :: Python :: 3.11
Classifier: Programming Language :: Python :: 3.12
Classifier: Programming Language :: Python :: 3.13
Classifier: Topic :: Software Development :: Libraries :: Python Modules
Provides-Extra: langdetect
Provides-Extra: openai
Provides-Extra: spacy
Provides-Extra: stanza
Provides-Extra: tiktoken
Requires-Dist: langdetect (>=1.0.9) ; extra == "langdetect"
Requires-Dist: openai (>=1.88.0) ; extra == "openai"
Requires-Dist: spacy (>=3.7.0) ; extra == "spacy"
Requires-Dist: stanza (>=1.4.2) ; extra == "stanza"
Requires-Dist: tiktoken (>=0.9.0) ; extra == "tiktoken"
Requires-Dist: typing-extensions (>=4.14.1,<5.0.0)
Project-URL: Repository, https://github.com/gioelecrispo/chunkipy
